sidra_helpers/__init__.py
sidra_helpers/sidra_helpers.py
sidra_helpers-1.0.7.dist-info/LICENSE
sidra_helpers-1.0.7.dist-info/METADATA
sidra_helpers-1.0.7.dist-info/WHEEL
sidra_helpers-1.0.7.dist-info/top_level.txt
sidra_helpers-1.0.7.dist-info/RECORD
