Metadata-Version: 2.1
Name: sidra-helpers
Version: 1.0.7
Summary: Helper functions made for personal use to work with the SIDRA API
Home-page: https://github.com/GuilhermeFrainer/sidra_helpers
Author: Guilherme da Silva Frainer
Author-email: guilherme.sfrainer@gmail.com
Classifier: Programming Language :: Python :: 3
Classifier: License :: OSI Approved :: MIT License
Classifier: Operating System :: OS Independent
Requires-Python: >=3.7
License-File: LICENSE
Requires-Dist: xlsxwriter
